README.md
setup.py
crypto_extract.egg-info/PKG-INFO
crypto_extract.egg-info/SOURCES.txt
crypto_extract.egg-info/dependency_links.txt
crypto_extract.egg-info/entry_points.txt
crypto_extract.egg-info/requires.txt
crypto_extract.egg-info/top_level.txt
ethereum/__init__.py
ethereum/logging_util.py
ethereum/cli/__init__.py
ethereum/cli/extract_blocks_and_transactions.py
ethereum/cli/extract_traces.py
ethereum/cli/extract_verified_contract.py
ethereum/raw_data/__init__.py
ethereum/raw_data/aws_utils.py
ethereum/raw_data/etl_command_wrapper.py
ethereum/raw_data/resource.py
ethereum/raw_data/resource_stage.py
ethereum/raw_data/job/__init__.py
ethereum/raw_data/job/base_job.py
ethereum/raw_data/job/block_tx_extract_job.py
ethereum/raw_data/job/extract_job.py
ethereum/raw_data/job/trace_extract_job.py
ethereum/raw_data/job/verified_contract_extract_job.py