Metadata-Version: 2.1
Name: crypto-extract
Version: 1.4.5
Summary: Tools for exporting Ethereum blockchain data to Redshift
Home-page: https://github.com/tellery/crypto-extract
Author: songv
Author-email: songwei@iftech.io
License: UNKNOWN
Project-URL: Bug Reports, https://github.com/tellery/crypto-extract/issues
Project-URL: Source, https://github.com/tellery/crypto-extract
Keywords: ethereum
Platform: UNKNOWN
Classifier: Development Status :: 5 - Production/Stable
Classifier: Intended Audience :: Developers
Classifier: License :: OSI Approved :: MIT License
Classifier: Programming Language :: Python :: 3
Classifier: Programming Language :: Python :: 3.6
Classifier: Programming Language :: Python :: 3.7
Classifier: Programming Language :: Python :: 3.8
Classifier: Programming Language :: Python :: 3.9
Requires-Python: >=3.6,<4
